qr_server/Config.py
qr_server/FileManager.py
qr_server/FlaskServer.py
qr_server/Logger.py
qr_server/Repository.py
qr_server/RoleManager.py
qr_server/Server.py
qr_server/TokenManager.py
qr_server/__init__.py
qr_server/dict_parsing.py
qr_server/dto_converter.py
qr_server-1.0.11.dist-info/LICENSE
qr_server-1.0.11.dist-info/METADATA
qr_server-1.0.11.dist-info/WHEEL
qr_server-1.0.11.dist-info/top_level.txt
qr_server-1.0.11.dist-info/RECORD
