Metadata-Version: 2.1
Name: qr-server
Version: 1.0.11
Summary: console app builder
Home-page: https://github.com/Kurush7/qr_server
Author: Kurush
Author-email: ze17@ya.ru
License: UNKNOWN
Platform: UNKNOWN
Classifier: Programming Language :: Python :: 3.6
Classifier: Operating System :: OS Independent
Requires-Python: >=3.6
License-File: LICENSE
Requires-Dist: qrookDB
Requires-Dist: Flask (==2.0.1)
Requires-Dist: Flask-HTTPAuth (==4.2.0)
Requires-Dist: Flask-Cors (==3.0.10)
Requires-Dist: Jinja2 (==3.0.1)
Requires-Dist: confuse
Requires-Dist: PyJWT
Requires-Dist: psycopg2-binary (==2.8.6)
Requires-Dist: Inject
Requires-Dist: requests
Requires-Dist: gevent
